[
	{
		"company_id": 2,
		"alias": ["Saudi Aramco", "Saudi Arabian Oil Co.", "Saudi Arabian Oil Company (Saudi Aramco)"]
	},
	{
		"company_id": 3,
		"alias": ["J.P. Morgan"]
	},
	{
		"company_id": 13,
		"alias": ["Samsung", "Samsung Electronics", "Samsung SDI"]
	},
	{
		"company_id": 21,
		"alias": ["UnitedHealthcare", "UnitedHealthcare Community Plan of Indiana"]
	},
	{
		"company_id": 27,
		"alias": ["Tencent"]
	},
	{
		"company_id": 29,
		"alias": ["Postal Savings Bank of China (PSBC)", "PSBC", "Postal Savings Bank of China"]
	},
	{
		"company_id": 30,
		"alias": ["CMLink"]
	},
	{
		"company_id": 36,
		"alias": ["Goldman Sachs"]
	},
	{
		"company_id": 43,
		"alias": ["SoftBank", "SoftBank Group Corp"]
	},
	{
		"company_id": 52,
		"alias": ["NTT Ltd.", "NTT", "NTT Corporation"]
	},
	{
		"company_id": 53,
		"alias": ["Reliance-bp"]
	},
	{
		"company_id": 59,
		"alias": ["Ford"]
	},
	{
		"company_id": 72,
		"alias": ["AIA"]
	},
	{
		"company_id": 86,
		"alias": ["Merck"]
	},
	{
		"company_id": 88,
		"alias": ["Scotiabank", "Scotia"]
	},
	{
		"company_id": 89,
		"alias": ["AIG"]
	},
	{
		"company_id": 91,
		"alias": ["Cisco"]
	},
	{
		"company_id": 93,
		"alias": ["Disney"]
	},
	{
		"company_id": 99,
		"alias": ["UPS"]
	},
	{
		"company_id": 104,
		"alias": ["CSCEC"]
	},
	{
		"company_id": 107,
		"alias": ["SPDB"]
	},
	{
		"company_id": 116,
		"alias": ["BMO"]
	},
	{
		"company_id": 120,
		"alias": ["Crédit Agricole"]
	},
	{
		"company_id": 121,
		"alias": ["Airbus"]
	},
	{
		"company_id": 131,
		"alias": ["U.S. Bancorp"]
	},
	{
		"company_id": 137,
		"alias": ["Itaú Unibanco"]
	},
	{
		"company_id": 150,
		"alias": ["BBVA"]
	},
	{
		"company_id": 151,
		"alias": ["Tesla"]
	},
	{
		"company_id": 160,
		"alias": ["Maersk", "A.P. Moller - Maersk"]
	},
	{
		"company_id": 164,
		"alias": ["PNC", "PNC Canada"]
	},
	{
		"company_id": 166,
		"alias": ["LUKOIL"]
	},
	{
		"company_id": 169,
		"alias": ["SK hynix"]
	},
	{
		"company_id": 188,
		"alias": ["CIBC"]
	},
	{
		"company_id": 192,
		"alias": ["Fubon", "Fubon Life of Taiwan"]
	},
	{
		"company_id": 198,
		"alias": ["NAB"]
	},
	{
		"company_id": 217,
		"alias": ["OCBC"]
	},
	{
		"company_id": 223,
		"alias": ["GE"]
	},
	{
		"company_id": 224,
		"alias": ["Societe Generale", "Societe Generale Group"]
	},
	{
		"company_id": 228,
		"alias": ["ONGC"]
	},
	{
		"company_id": 231,
		"alias": ["NV Gotion", "Gotion Hi-tech Co."]
	},
	{
		"company_id": 233,
		"alias": ["CNRL"]
	},
	{
		"company_id": 236,
		"alias": ["Archer-Daniels-Midland Company (ADM)", "Archer-Daniels-Midland Company", "ADM"]
	},
	{
		"company_id": 245,
		"alias": ["CCCC"]
	},
	{
		"company_id": 250,
		"alias": ["Power Corporation of Canada (TSX: POW)", "Power Corporation of Canada", "POW", "Power Corporation"]
	},
	{
		"company_id": 251,
		"alias": ["QNB", "QNB Group"]
	},
	{
		"company_id": 260,
		"alias": ["Seven & i Holdings"]
	},
	{
		"company_id": 265,
		"alias": ["BNY Mellon", "BNY", "Mellon"]
	},
	{
		"company_id": 291,
		"alias": ["Baosteel"]
	},
	{
		"company_id": 297,
		"alias": ["CATL"]
	},
	{
		"company_id": 304,
		"alias": ["Intercontinental Exchange (ICE)", "ICE", "Intercontinental Exchange"]
	},
	{
		"company_id": 305,
		"alias": ["The TJX Companies, Inc. (TJX)", "TJX"]
	},
	{
		"company_id": 316,
		"alias": ["ADP"]
	},
	{
		"company_id": 326,
		"alias": ["Saudi National Bank"]
	},
	{
		"company_id": 329,
		"alias": ["Saudi Arabia"]
	},
	{
		"company_id": 334,
		"alias": ["Couche-Tard"]
	},
	{
		"company_id": 339,
		"alias": ["Marsh McLennan", "Marsh McLennan (NYSE: MMC)", "MMC"]
	},
	{
		"company_id": 348,
		"alias": ["SLB"]
	},
	{
		"company_id": 350,
		"alias": ["BRI", "Bank Rakyat Indonesia", "Bank Rakyat Indonesia (Persero) Tbk", "Bank Rakyat Indonesia (BRI)"]
	},
	{
		"company_id": 356,
		"alias": ["DuPont"]
	},
	{
		"company_id": 358,
		"alias": ["India's oil"]
	},
	{
		"company_id": 360,
		"alias": ["Kraft Heinz Co.", "Kraft Heinz", "Heinz"]
	},
	{
		"company_id": 366,
		"alias": ["UOB"]
	},
	{
		"company_id": 395,
		"alias": ["CMSK"]
	},
	{
		"company_id": 399,
		"alias": ["Johnson Controls"]
	},
	{
		"company_id": 401,
		"alias": ["stc"]
	},
	{
		"company_id": 415,
		"alias": ["Greenland Holdings Corp.", "Greenland Group Canada"]
	},
	{
		"company_id": 463,
		"alias": ["Evergrande", "Evergrande Group"]
	},
	{
		"company_id": 492,
		"alias": ["Con Edison"]
	},
	{
		"company_id": 494,
		"alias": ["Evergreen Marine Corp. (Taiwan) Ltd.", "Evergreen Marine Corp. (Taiwan)"]
	},
	{
		"company_id": 496,
		"alias": ["SCCIG"]
	},
	{
		"company_id": 503,
		"alias": ["Fujifilm", "FUJIFILM", "Fuji"]
	},
	{
		"company_id": 518,
		"alias": ["Volvo"]
	},
	{
		"company_id": 520,
		"alias": ["Ørsted"]
	},
	{
		"company_id": 550,
		"alias": ["Air Products and Chemicals, Inc.", "Air Products and Chemicals", "Air Products"]
	},
	{
		"company_id": 563,
		"alias": ["AMD"]
	},
	{
		"company_id": 576,
		"alias": ["Regions Bank"]
	},
	{
		"company_id": 578,
		"alias": ["Raymond James Ltd."]
	},
	{
		"company_id": 592,
		"alias": ["Parker Hannifin Corporation", "Parker Hannifin", "Parker"]
	},
	{
		"company_id": 593,
		"alias": ["Vedanta Ltd", "Vedanta Ltd.", "Vedanta"]
	},
	{
		"company_id": 598,
		"alias": ["Rogers"]
	},
	{
		"company_id": 603,
		"alias": ["SMTB"]
	},
	{
		"company_id": 606,
		"alias": ["EnBW"]
	},
	{
		"company_id": 616,
		"alias": ["Haliburton"]
	},
	{
		"company_id": 617,
		"alias": ["Metallurgical Corporation of China", "MCC"]
	},
	{
		"company_id": 619,
		"alias": ["Heidelberg", "Heidelberg Materials"]
	},
	{
		"company_id": 633,
		"alias": ["China Tower"]
	},
	{
		"company_id": 637,
		"alias": ["Shimao Group", "Shimao"]
	},
	{
		"company_id": 646,
		"alias": ["IHC"]
	},
	{
		"company_id": 663,
		"alias": ["Fidelity National Information Services Inc. (NYSE: FIS)", "FIS", "Fidelity National Information Services", "Fidelity National Information Services Inc.", "Fidelity National Information (FIS)"]
	},
	{
		"company_id": 672,
		"alias": ["Porsche SE", "Porsche"]
	},
	{
		"company_id": 673,
		"alias": ["H&M"]
	},
	{
		"company_id": 677,
		"alias": ["Ross Dress for Less", "Ross"]
	},
	{
		"company_id": 687,
		"alias": ["HKEX"]
	},
	{
		"company_id": 703,
		"alias": ["Veolia"]
	},
	{
		"company_id": 704,
		"alias": ["O'Reilly", "O'Reilly Auto Parts"]
	},
	{
		"company_id": 718,
		"alias": ["KEPCO"]
	},
	{
		"company_id": 720,
		"alias": ["MHI", "Mitsubishi", "Mitsui"]
	},
	{
		"company_id": 726,
		"alias": ["AISIN CORPORATION"]
	},
	{
		"company_id": 747,
		"alias": ["Hydro"]
	},
	{
		"company_id": 761,
		"alias": ["JR East", "JR"]
	},
	{
		"company_id": 762,
		"alias": ["ADCB"]
	},
	{
		"company_id": 815,
		"alias": ["CRCB"]
	},
	{
		"company_id": 855,
		"alias": ["CITS"]
	},
	{
		"company_id": 862,
		"alias": ["Shanghai Port International"]
	},
	{
		"company_id": 770,
		"alias": ["Fortis (Canada)", "Fortis"]
	},
	{
		"company_id": 773,
		"alias": ["BTG Pactual", "BTG"]
	},
	{
		"company_id": 801,
		"alias": ["U. S. Steel", "Steel"]
	},
	{
		"company_id": 808,
		"alias": ["HCLTech", "HCL"]
	},
	{
		"company_id": 821,
		"alias": ["POWERGRID"]
	},
	{
		"company_id": 823,
		"alias": ["NLMK", "NLMK Group"]
	},
	{
		"company_id": 829,
		"alias": ["ZSHL"]
	},
	{
		"company_id": 836,
		"alias": ["TNB"]
	},
	{
		"company_id": 841,
		"alias": ["TEPCO"]
	},
	{
		"company_id": 843,
		"alias": ["Hershey"]
	},
	{
		"company_id": 845,
		"alias": ["PGNiG"]
	},
	{
		"company_id": 846,
		"alias": ["MTN Zambia", "MTN"]
	},
	{
		"company_id": 851,
		"alias": ["BSHSR"]
	},
	{
		"company_id": 852,
		"alias": ["Chalco"]
	},
	{
		"company_id": 853,
		"alias": ["KEPCO"]
	},
	{
		"company_id": 858,
		"alias": ["T. Rowe Price"]
	},
	{
		"company_id": 867,
		"alias": ["Mitsui O.S.K. Lines", "Mitsui O.S.K. Lines, Ltd. (MOL)", "(MOL)", "MOL"]
	},
	{
		"company_id": 868,
		"alias": ["SAB"]
	},
	{
		"company_id": 871,
		"alias": ["August Home"]
	},
	{
		"company_id": 881,
		"alias": ["PSEG"]
	},
	{
		"company_id": 882,
		"alias": ["En+ Group"]
	},
	{
		"company_id": 898,
		"alias": ["CMS"]
	},
	{
		"company_id": 913,
		"alias": ["ASUS Global", "ASUS"]
	},
	{
		"company_id": 917,
		"alias": ["CMOC Group Limited", "CMOC Group", "CMOC"]
	},
	{
		"company_id": 924,
		"alias": ["Grainger Canada", "Grainger"]
	},
	{
		"company_id": 934,
		"alias": ["Zhongnan Construction Group", "Zhongnan"]
	},
	{
		"company_id": 937,
		"alias": ["SMIC"]
	},
	{
		"company_id": 946,
		"alias": ["Julius Baer International", "Julius Baer"]
	},
	{
		"company_id": 951,
		"alias": ["SRCB"]
	},
	{
		"company_id": 961,
		"alias": ["Gerdau (Cosigua)"]
	},
	{
		"company_id": 963,
		"alias": ["QIB Group", "QIB"]
	},
	{
		"company_id": 973,
		"alias": ["Molson Coors", "Molson Coors Beverage Company"]
	},
	{
		"company_id": 977,
		"alias": ["CIM"]
	},
	{
		"company_id": 1002,
		"alias": ["Eletrobras"]
	},
	{
		"company_id": 1003,
		"alias": ["Mengniu Dairy", "Mengniu"]
	},
	{
		"company_id": 1007,
		"alias": ["SMIC"]
	},
	{
		"company_id": 1010,
		"alias": ["TCFHC"]
	},
	{
		"company_id": 1021,
		"alias": ["iA Financial Group", "iA Financial", "iA Group"]
	},
	{
		"company_id": 1025,
		"alias": ["Baloise Group", "Baloise"]
	},
	{
		"company_id": 1027,
		"alias": ["JLL Canada", "JLL"]
	},
	{
		"company_id": 1029,
		"alias": ["Daiwa"]
	},
	{
		"company_id": 1030,
		"alias": ["Lufthansa"]
	},
	{
		"company_id": 1035,
		"alias": ["Mizrahi-Tefahot Bank"]
	},
	{
		"company_id": 1051,
		"alias": ["Teva Canada", "Teva"]
	},
	{
		"company_id": 1062,
		"alias": ["Mahindra"]
	},
	{
		"company_id": 1066,
		"alias": ["AkzoNobel"]
	},
	{
		"company_id": 1069,
		"alias": ["Randstad"]
	},
	{
		"company_id": 1070,
		"alias": ["Sibanye-Stillwater", "Sibanye", "Stillwater"]
	},
	{
		"company_id": 1074,
		"alias": ["FWONA"]
	},
	{
		"company_id": 1078,
		"alias": ["Shougang"]
	},
	{
		"company_id": 1082,
		"alias": ["Mindray"]
	},
	{
		"company_id": 1093,
		"alias": ["TIM"]
	},
	{
		"company_id": 1097,
		"alias": ["Dassault Systèmes", "Dassault"]
	},
	{
		"company_id": 1102,
		"alias": ["Longyuan Power"]
	},
	{
		"company_id": 1135,
		"alias": ["Sainsbury"]
	},
	{
		"company_id": 1138,
		"alias": ["AUO"]
	},
	{
		"company_id": 1147,
		"alias": ["Impala"]
	},
	{
		"company_id": 1150,
		"alias": ["Rolls-Royce"]
	},
	{
		"company_id": 1166,
		"alias": ["CLI"]
	},
	{
		"company_id": 1167,
		"alias": ["Fastighets AB Balder", "Balder"]
	},
	{
		"company_id": 1172,
		"alias": ["New World (video game)", "New World"]
	},
	{
		"company_id": 1177,
		"alias": ["ChemChina"]
	},
	{
		"company_id": 1183,
		"alias": ["Zoom"]
	},
	{
		"company_id": 1184,
		"alias": ["MMK"]
	},
	{
		"company_id": 1191,
		"alias": ["CR Pharmaceutical", "CR"]
	},
	{
		"company_id": 1213,
		"alias": ["EQT Growth", "EQT"]
	},
	{
		"company_id": 1214,
		"alias": ["GAIL (India) Limited", "GAIL (India)", "GAIL", "Gail"]
	},
	{
		"company_id": 1215,
		"alias": ["Baotou Steel", "Baotou"]
	},
	{
		"company_id": 1219,
		"alias": ["Carnival Venezia", "Carnival"]
	},
	{
		"company_id": 1226,
		"alias": ["ORI"]
	},
	{
		"company_id": 1252,
		"alias": ["SXFWF"]
	},
	{
		"company_id": 1267,
		"alias": ["Changan Automobile", "Changan"]
	},
	{
		"company_id": 1276,
		"alias": ["Grupo Financiero Inbursa"]
	},
	{
		"company_id": 1277,
		"alias": ["DRC Bank", "DRC"]
	},
	{
		"company_id": 1280,
		"alias": ["Banco Sabadell"]
	},
	{
		"company_id": 1289,
		"alias": ["SBB", "Samhällsbyggnadsbolaget i Norden AB (publ) (SBB)"]
	},
	{
		"company_id": 1300,
		"alias": ["CFLD"]
	},
	{
		"company_id": 1304,
		"alias": ["CR Power", "CR"]
	},
	{
		"company_id": 1309,
		"alias": ["anb"]
	},
	{
		"company_id": 1313,
		"alias": ["China Three Gorges Renewables (Group) Co., Ltd. (CTGR)", "China Three Gorges Renewables (Group)", "(CTGR)", "CTGR", "China Three Gorges Renewables"]
	},
	{
		"company_id": 1314,
		"alias": ["EA"]
	},
	{
		"company_id": 1341,
		"alias": ["StoneX"]
	},
	{
		"company_id": 1345,
		"alias": ["ENN NG"]
	},
	{
		"company_id": 1346,
		"alias": ["Phonix Holdings Pty Ltd", "Phonix Holdings", "Phonix"]
	},
	{
		"company_id": 1351,
		"alias": ["Daqo New Energy", "Daqo"]
	},
	{
		"company_id": 1356,
		"alias": ["COGOGL"]
	},
	{
		"company_id": 1360,
		"alias": ["LEG Immobilien SE", "LEG"]
	},
	{
		"company_id": 1361,
		"alias": ["Sun Pharma", "Sun Pharmaceutical Industries Ltd."]
	},
	{
		"company_id": 1368,
		"alias": ["XCMG"]
	},
	{
		"company_id": 1374,
		"alias": ["Galp"]
	},
	{
		"company_id": 1383,
		"alias": ["Taigang Stainless Steel", "Taigang Stainless", "Taigang"]
	},
	{
		"company_id": 1401,
		"alias": ["Packaging Corporation of America (PCA)", "Packaging Corporation of America", "PCA"]
	},
	{
		"company_id": 1412,
		"alias": ["BCD"]
	},
	{
		"company_id": 1419,
		"alias": ["CGAS"]
	},
	{
		"company_id": 1423,
		"alias": ["Wabtec", "WAB", "(NYSE: WAB)"]
	},
	{
		"company_id": 1424,
		"alias": ["K Line"]
	},
	{
		"company_id": 1467,
		"alias": ["First Citizens Bank (NC)"]
	},
	{
		"company_id": 264,
		"alias": ["DENSO"]
	},
	{
		"company_id": 282,
		"alias": ["Kia"]
	},
	{
		"company_id": 285,
		"alias": ["POSCO Chemical", "POSCO"]
	},
	{
		"company_id": 344,
		"alias": ["ORIX Group", "ORIX"]
	},
	{
		"company_id": 345,
		"alias": ["CITIC Securities", "CITIC"]
	},
	{
		"company_id": 490,
		"alias": ["FEMSA"]
	},
	{
		"company_id": 491,
		"alias": ["PACCAR"]
	},
	{
		"company_id": 554,
		"alias": ["Telus"]
	},
	{
		"company_id": 610,
		"alias": ["ONEOK", "ONEOK, Inc. (NYSE: OKE)"]
	},
	{
		"company_id": 723,
		"alias": ["LONGi Green Energy Technology", "LONGi"]
	},
	{
		"company_id": 807,
		"alias": ["MAPFRE"]
	},
	{
		"company_id": 827,
		"alias": ["SEGRO"]
	},
	{
		"company_id": 873,
		"alias": ["ASR Nederland N.V. (a.s.r.)", "ASR", "ASR Nederland N.V.", "a.s.r.", "A.S.R."]
	},
	{
		"company_id": 895,
		"alias": ["KONE"]
	},
	{
		"company_id": 902,
		"alias": ["Sabancı Holding", "Sabancı"]
	},
	{
		"company_id": 1005,
		"alias": ["E.SUN Financial", "E.SUN Financial Holding Co., Ltd. (E.SUN FHC)", "E.SUN", "E.SUN FHC"]
	},
	{
		"company_id": 1013,
		"alias": ["FANUC GLOBAL", "FANUC", "FANUC America"]
	},
	{
		"company_id": 1053,
		"alias": ["VERBUND"]
	},
	{
		"company_id": 1055,
		"alias": ["Bank of Chengdu", "BoCD", "Bank of Chengdu (BoCD)"]
	},
	{
		"company_id": 1180,
		"alias": ["SECOM"]
	},
	{
		"company_id": 1236,
		"alias": ["PCG", "PETRONAS Chemicals Group Bhd. (PCG)", "PETRONAS", "PETRONAS Chemicals"]
	},
	{
		"company_id": 1246,
		"alias": ["HD Hyundai", "Hyundai"]
	},
	{
		"company_id": 1273,
		"alias": ["DICK'S Sporting Goods", "DICK'S", "Dick's"]
	},
	{
		"company_id": 1282,
		"alias": ["WuXi AppTec", "WuXi"]
	},
	{
		"company_id": 1295,
		"alias": ["AMETEK, Inc. (NYSE: AME)", "AMETEK", "AME"]
	},
	{
		"company_id": 1330,
		"alias": ["CJ CheilJedang", "CJ", "CheilJedang"]
	},
	{
		"company_id": 1418,
		"alias": ["Airbnb"]
	},
	{
		"company_id": 1428,
		"alias": ["Attijariwafa bank", "Attijariwafa"]
	},
	{
		"company_id": 1436,
		"alias": ["THOR Industries", "THOR"]
	},
	{
		"company_id": 1432,
		"alias": ["Suntory Kyushu Kumamoto Plant", "Suntory", "Suntory Kyushu", "Suntory Kyushu Kumamoto"]
	},
	{
		"company_id": 1519,
		"alias": ["Wharf (Holdings)"]
	},
	{
		"company_id": 1600,
		"alias": ["ZTO Express (Cayman)"]
	},
	{
		"company_id": 1683,
		"alias": ["China Resources Beer (Holdings)"]
	},
	{
		"company_id": 1825,
		"alias": ["ICON (Ireland)"]
	},
	{
		"company_id": 1835,
		"alias": ["Titan (India)"]
	},
	{
		"company_id": 16,
		"alias": ["Ping An Health", "Ping An Good Doctor"]
	},
	{
		"company_id": 105,
		"alias": ["SBI"]
	},
	{
		"company_id": 60,
		"alias": ["LVMH"]
	},
	{
		"company_id": 58,
		"alias": ["TSMC"]
	},
	{
		"company_id": 92,
		"alias": ["AB InBev"]
	},
	{
		"company_id": 102,
		"alias": ["Honda"]
	},
	{
		"company_id": 105,
		"alias": ["SBI"]
	},
	{
		"company_id": 189,
		"alias": ["Poly Group"]
	},
	{
		"company_id": 207,
		"alias": ["CPIC"]
	},
	{
		"company_id": 216,
		"alias": ["CR Land"]
	},
	{
		"company_id": 245,
		"alias": ["CCC"]
	},
	{
		"company_id": 271,
		"alias": ["Merck KGaA, Darmstadt, Germany"]
	},
	{
		"company_id": 272,
		"alias": ["CAIXABANK"]
	},
	{
		"company_id": 346,
		"alias": ["FAB"]
	},
	{
		"company_id": 355,
		"alias": ["Bank of Jiangsu"]
	},
	{
		"company_id": 364,
		"alias": ["JT"]
	},
	{
		"company_id": 380,
		"alias": ["POWERCHINA"]
	},
	{
		"company_id": 392,
		"alias": ["SHKP"]
	},
	{
		"company_id": 399,
		"alias": ["JCI"]
	},
	{
		"company_id": 403,
		"alias": ["CN"]
	},
	{
		"company_id": 428,
		"alias": ["Emerson"]
	},
	{
		"company_id": 450,
		"alias": ["Naturgy"]
	},
	{
		"company_id": 476,
		"alias": ["NCI"]
	},
	{
		"company_id": 542,
		"alias": ["CPKC Railway"]
	},
	{
		"company_id": 544,
		"alias": ["TEL"]
	},
	{
		"company_id": 550,
		"alias": ["APD"]
	},
	{
		"company_id": 558,
		"alias": ["CZB"]
	},
	{
		"company_id": 7,
		"alias": ["ABC"]
	},
	{
		"company_id": 57,
		"alias": ["MUFG Bank", "MUFG"]
	},
	{
		"company_id": 71,
		"alias": ["Roche"]
	},
	{
		"company_id": 152,
		"alias": ["John Deere"]
	},
	{
		"company_id": 197,
		"alias": ["Vanke"]
	}
]
